greendeck_logging/__init__.py
greendeck_logging/logging_function.py
greendeck_logging/save_as_single.py
greendeck_logging/save_as_stack.py
greendeck_logging-0.1.9.dist-info/LICENSE
greendeck_logging-0.1.9.dist-info/METADATA
greendeck_logging-0.1.9.dist-info/WHEEL
greendeck_logging-0.1.9.dist-info/top_level.txt
greendeck_logging-0.1.9.dist-info/RECORD
