Metadata-Version: 2.1
Name: greendeck-logging
Version: 0.1.9
Summary: Greendeck logging package
Home-page: https://github.com/abhay-kum/greendeck-logging.git
Author: abhay kumar
Author-email: abhay.kumar@greendeck.co
License: UNKNOWN
Platform: UNKNOWN
Classifier: Programming Language :: Python :: 3
Classifier: License :: OSI Approved :: MIT License
Classifier: Operating System :: OS Independent
Requires-Dist: elasticsearch
